electronic_symbol_generator_for_cad/__init__.py
electronic_symbol_generator_for_cad/__main__.py
electronic_symbol_generator_for_cad/engine/__init__.py
electronic_symbol_generator_for_cad/engine/layout_managers.py
electronic_symbol_generator_for_cad/engine/models.py
electronic_symbol_generator_for_cad/kicad5/__init__.py
electronic_symbol_generator_for_cad/kicad5/comments.py
electronic_symbol_generator_for_cad/kicad5/metrics.py
electronic_symbol_generator_for_cad/kicad5/pins.py
electronic_symbol_generator_for_cad/kicad5/symbolGenerator.py
electronic_symbol_generator_for_cad/kicad5/symbolGenerator_fmu.py
electronic_symbol_generator_for_cad/kicad5/symbolGenerator_fsu.py
electronic_symbol_generator_for_cad/kicad5/symbolGenerator_psu.py
electronic_symbol_generator_for_cad/kicad5/symbols.py
electronic_symbol_generator_for_cad/sygen.py
electronic_symbol_generator_for_cad/symbolGenerator.py
electronic_symbol_generator_for_cad_by_sporniket-0.0.3.dist-info/METADATA
electronic_symbol_generator_for_cad_by_sporniket-0.0.3.dist-info/WHEEL
electronic_symbol_generator_for_cad_by_sporniket-0.0.3.dist-info/entry_points.txt
electronic_symbol_generator_for_cad_by_sporniket-0.0.3.dist-info/RECORD
