Metadata-Version: 2.1
Name: electronic-symbol-generator-for-cad-by-sporniket
Version: 0.0.3
Summary: Electronic symbol generator for CAD, a library with a command line interface to generate symbols of electronic packages for electronic CAD suites like Kicad.
Keywords: Kicad,symbol generator
Author-Email: Sporniket <sporniket.studio@gmail.com>
License: GPL-3.0-or-later
Project-URL: homepage, https://github.com/sporniket/electronic-symbol-generator-for-cad
Project-URL: repository, https://github.com/sporniket/electronic-symbol-generator-for-cad
Project-URL: bug-tracker, https://github.com/sporniket/electronic-symbol-generator-for-cad/issues
Requires-Python: >=3.12
Requires-Dist: electronic-package-descriptor-by-sporniket<1.1.0
